llama_index/tools/openapi/__init__.py
llama_index/tools/openapi/base.py
llama_index_tools_openapi-0.5.1.dist-info/METADATA
llama_index_tools_openapi-0.5.1.dist-info/WHEEL
llama_index_tools_openapi-0.5.1.dist-info/licenses/LICENSE
llama_index_tools_openapi-0.5.1.dist-info/RECORD
